[
    {
        "belongsTo": "test3@test.com",
        "userComment": "                        dfgdfg"
    },
    {
        "belongsTo": "test3@test.com",
        "userComment": "                        dfgdfg"
    },
    {
        "belongsTo": "test3@test.com",
        "userComment": "                        sfsdfsd"
    },
    {
        "belongsTo": "test3@test.com",
        "userComment": "                        sfsdfsd"
    },
    {
        "belongsTo": "test3@test.com",
        "userComment": "                        sfsdfsd"
    },
    {
        "belongsTo": "test3@test.com",
        "userComment": "                        sdfsdf"
    },
    {
        "belongsTo": "test3@test.com",
        "userComment": "                        sdfsdf"
    },
    {
        "belongsTo": "test3@test.com",
        "userComment": "                        sdfsdf"
    },
    {
        "belongsTo": "test3@test.com",
        "userComment": "                        dfsdf"
    },
    {
        "belongsTo": "test3@test.com",
        "userComment": "                        dfsdf"
    },
    {
        "belongsTo": "test3@test.com",
        "userComment": "                        dfsdf"
    },
    {
        "belongsTo": "test3@test.com",
        "userComment": "               Hello this is the new test        "
    }
]